kicadfiles/CLASSES.md
kicadfiles/__init__.py
kicadfiles/__version__.py
kicadfiles/advanced_graphics.py
kicadfiles/base_element.md
kicadfiles/base_element.py
kicadfiles/base_types.py
kicadfiles/board_layout.py
kicadfiles/design_rules.py
kicadfiles/enums.py
kicadfiles/footprint_library.py
kicadfiles/json_base_element.py
kicadfiles/library_tables.py
kicadfiles/pad_and_drill.py
kicadfiles/primitive_graphics.py
kicadfiles/project_settings.py
kicadfiles/schematic_system.py
kicadfiles/sexpdata.py
kicadfiles/sexpr_parser.py
kicadfiles/symbol_library.py
kicadfiles/templates.py
kicadfiles/text_and_documents.py
kicadfiles/zone_system.py
kicadfiles-1.0.5.dist-info/licenses/LICENSE
kicadfiles-1.0.5.dist-info/METADATA
kicadfiles-1.0.5.dist-info/WHEEL
kicadfiles-1.0.5.dist-info/top_level.txt
kicadfiles-1.0.5.dist-info/RECORD
