Metadata-Version: 2.4
Name: kicadfiles
Version: 1.0.5
Summary: A comprehensive Python library for parsing and manipulating KiCad file formats
Author-email: Steffen-W <steffen@example.com>
License-Expression: MIT
Project-URL: Homepage, https://github.com/Steffen-W/KiCadFiles
Project-URL: Documentation, https://steffen-w.github.io/KiCadFiles/
Project-URL: Repository, https://github.com/Steffen-W/KiCadFiles.git
Project-URL: Bug Tracker, https://github.com/Steffen-W/KiCadFiles/issues
Keywords: kicad,eda,electronics,pcb,schematic,parser
Classifier: Development Status :: 4 - Beta
Classifier: Intended Audience :: Developers
Classifier: Intended Audience :: Science/Research
Classifier: Operating System :: OS Independent
Classifier: Programming Language :: Python :: 3
Classifier: Programming Language :: Python :: 3.9
Classifier: Programming Language :: Python :: 3.10
Classifier: Programming Language :: Python :: 3.11
Classifier: Programming Language :: Python :: 3.12
Classifier: Topic :: Scientific/Engineering :: Electronic Design Automation (EDA)
Classifier: Topic :: Software Development :: Libraries :: Python Modules
Requires-Python: >=3.9
License-File: LICENSE
Provides-Extra: dev
Requires-Dist: pytest>=7.0; extra == "dev"
Requires-Dist: pytest-cov; extra == "dev"
Requires-Dist: black; extra == "dev"
Requires-Dist: isort; extra == "dev"
Requires-Dist: flake8; extra == "dev"
Requires-Dist: mypy; extra == "dev"
Requires-Dist: pyright; extra == "dev"
Provides-Extra: docs
Requires-Dist: sphinx; extra == "docs"
Requires-Dist: sphinx-rtd-theme; extra == "docs"
Dynamic: license-file
